{"type":"PR","pr":{"number":73,"head":"bf8225a368e2d7aa6cfec85be90103c39c4ba3ed"},"user":"Antonio","status":"pending_publish","branch":"cms/2019-03-25-amsterdam-exposed","collection":"blog","title":"Amsterdam Exposed","description":"This is an excerpt from the book: Amsterdam Exposed, an American's journey into the red light district. By David Wienir. ","objects":{"entry":{"path":"src/pages/blog/2019-03-25-amsterdam-exposed.md","sha":"429457385e5112bd66c86f4b7a3de45f154ad65d"},"files":[]},"timeStamp":"2019-05-27T18:57:01.303Z"}